TOPSIS_package/cli.py
topsis_analysis_irtebat-1.1.0.dist-info/LICENCE
topsis_analysis_irtebat-1.1.0.dist-info/METADATA
topsis_analysis_irtebat-1.1.0.dist-info/WHEEL
topsis_analysis_irtebat-1.1.0.dist-info/entry_points.txt
topsis_analysis_irtebat-1.1.0.dist-info/top_level.txt
topsis_analysis_irtebat-1.1.0.dist-info/RECORD
