Metadata-Version: 2.1
Name: topsis-analysis-irtebat
Version: 1.1.0
Summary: Topsis analysis of a csv file
Home-page: https://github.com/irtebat/topsis-analysis
Author: Irtebat
Author-email: irtebat.10@gmail.com
License: MIT
Platform: UNKNOWN
Classifier: License :: OSI Approved :: MIT License
Classifier: Programming Language :: Python :: 3
Classifier: Programming Language :: Python :: 3.7
Requires-Dist: numpy
Requires-Dist: pandas
